xlin/__init__.py
xlin/dataframe_util.py
xlin/datetime_util.py
xlin/file_util.py
xlin/image_util.py
xlin/jsonlist_util.py
xlin/metric.py
xlin/multiprocess_util.py
xlin/rich_xmap.py
xlin/statistic.py
xlin/text_util.py
xlin/timing_util.py
xlin/xlsx_util.py
xlin/yaml_util.py
xlin-0.2.25.dist-info/METADATA
xlin-0.2.25.dist-info/WHEEL
xlin-0.2.25.dist-info/licenses/LICENSE
xlin-0.2.25.dist-info/RECORD
