Metadata-Version: 2.4
Name: xlin
Version: 0.2.25
Summary: toolbox for LinXueyuan
License: MIT
License-File: LICENSE
Author: LinXueyuanStdio
Author-email: 23211526+LinXueyuanStdio@users.noreply.github.com
Classifier: License :: OSI Approved :: MIT License
Classifier: Programming Language :: Python :: 2
Classifier: Programming Language :: Python :: 2.7
Classifier: Programming Language :: Python :: 3
Classifier: Programming Language :: Python :: 3.4
Classifier: Programming Language :: Python :: 3.5
Classifier: Programming Language :: Python :: 3.6
Classifier: Programming Language :: Python :: 3.7
Classifier: Programming Language :: Python :: 3.8
Classifier: Programming Language :: Python :: 3.9
Classifier: Programming Language :: Python :: 3.10
Classifier: Programming Language :: Python :: 3.11
Classifier: Programming Language :: Python :: 3.12
Classifier: Programming Language :: Python :: 3.13
Classifier: Programming Language :: Python :: 3.14
Requires-Dist: Pillow
Requires-Dist: holidays
Requires-Dist: loguru
Requires-Dist: pandas
Requires-Dist: pyexcel
Requires-Dist: pyexcel-xls
Requires-Dist: pyexcel-xlsx
Requires-Dist: pyyaml
Requires-Dist: requests
Requires-Dist: tqdm
Requires-Dist: xlsxwriter
